MANIFEST.in
README.md
setup.cfg
setup.py
src/sql_column_parser/__init__.py
src/sql_column_parser/schemas.py
src/sql_column_parser/version.py
src/sql_column_parser.egg-info/PKG-INFO
src/sql_column_parser.egg-info/SOURCES.txt
src/sql_column_parser.egg-info/dependency_links.txt
src/sql_column_parser.egg-info/requires.txt
src/sql_column_parser.egg-info/top_level.txt