Metadata-Version: 2.1
Name: sql-column-parser
Version: 0.1.0
Summary: SQL Column Parser
Home-page: https://github.com/nymann/sql-column-parser
Maintainer: Kristian Nymann Jakobsen, Sebastian Olsen
Maintainer-email: kristian@nymann.dev, seol@itu.dk
License: GPL v3
Platform: UNKNOWN
Requires-Python: >= 3.8
